package_creation_tutorial/__init__.py
package_creation_tutorial/string_ops.py
nadia_by_package_creation_tutorial-0.2.0.dist-info/METADATA
nadia_by_package_creation_tutorial-0.2.0.dist-info/WHEEL
nadia_by_package_creation_tutorial-0.2.0.dist-info/RECORD
